authsrv/__init__.py
authsrv-0.0.9.dist-info/LICENSE
authsrv-0.0.9.dist-info/METADATA
authsrv-0.0.9.dist-info/WHEEL
authsrv-0.0.9.dist-info/top_level.txt
authsrv-0.0.9.dist-info/RECORD
