Metadata-Version: 2.1
Name: authsrv
Version: 0.0.9
Summary: wrapper for authsrv utilities
Home-page: https://github.com/unixtools/authsrv-python
Author: Nathan Neulinger
Author-email: nneul@neulinger.org
License: MIT
Keywords: authsrv
Platform: UNKNOWN
Classifier: Development Status :: 4 - Beta
Classifier: Intended Audience :: Developers
Classifier: License :: OSI Approved :: MIT License
Classifier: Operating System :: OS Independent
Classifier: Programming Language :: Python :: 3
Classifier: Programming Language :: Python
Classifier: Topic :: Software Development :: Libraries :: Python Modules
